assayo/index.html
assayo/assets/close.svg
assayo/assets/logo.svg
assayo/assets/achievements/adam.svg
assayo/assets/achievements/allRelease.svg
assayo/assets/achievements/commitsAfter1500.svg
assayo/assets/achievements/commitsAfter1800.svg
assayo/assets/achievements/commitsBefore1500.svg
assayo/assets/achievements/everyMessageLong.svg
assayo/assets/achievements/everyMessageShort.svg
assayo/assets/achievements/fileRush.svg
assayo/assets/achievements/firstCommit.svg
assayo/assets/achievements/firstLastCommit.svg
assayo/assets/achievements/hasCommitEveryTime.svg
assayo/assets/achievements/hasCommitFrom0to7.svg
assayo/assets/achievements/haveNotEmail.svg
assayo/assets/achievements/horoscope1.svg
assayo/assets/achievements/horoscope10.svg
assayo/assets/achievements/horoscope11.svg
assayo/assets/achievements/horoscope12.svg
assayo/assets/achievements/horoscope2.svg
assayo/assets/achievements/horoscope3.svg
assayo/assets/achievements/horoscope4.svg
assayo/assets/achievements/horoscope5.svg
assayo/assets/achievements/horoscope6.svg
assayo/assets/achievements/horoscope7.svg
assayo/assets/achievements/horoscope8.svg
assayo/assets/achievements/horoscope9.svg
assayo/assets/achievements/lastCommit.svg
assayo/assets/achievements/lessCommits.svg
assayo/assets/achievements/lessDaysForTask.svg
assayo/assets/achievements/lessDaysInProject.svg
assayo/assets/achievements/lessLazyDays.svg
assayo/assets/achievements/lessScopes.svg
assayo/assets/achievements/lessTasks.svg
assayo/assets/achievements/lessWorkDays.svg
assayo/assets/achievements/longFileName.svg
assayo/assets/achievements/longFilePath.svg
assayo/assets/achievements/longTask.svg
assayo/assets/achievements/longWaitPR.svg
assayo/assets/achievements/longestMessage.svg
assayo/assets/achievements/longestName.svg
assayo/assets/achievements/more2DaysForTask.svg
assayo/assets/achievements/more365DaysInProject.svg
assayo/assets/achievements/more3YearsInProject.svg
assayo/assets/achievements/more666DaysInProject.svg
assayo-0.1.2.dist-info/METADATA
assayo-0.1.2.dist-info/WHEEL
assayo-0.1.2.dist-info/entry_points.txt
assayo-0.1.2.dist-info/top_level.txt
assayo-0.1.2.dist-info/RECORD
