Metadata-Version: 2.4
Name: assayo
Version: 0.1.2
Summary: Visualization and analysis you git log. Creates HTML report about commits statistics. In addition the typical git stats, this package can show statistics by departments, tasks or determine the location of users.
Home-page: https://github.com/bakhirev/git-log-stat
Author: Aleksei Bakhirev
Author-email: Aleksei Bakhirev <alexey-bakhirev@yandex.ru>
License: GPL-3.0
Project-URL: Source, https://github.com/bakhirev/assayo
Project-URL: Tracker, https://github.com/bakhirev/assayo/issues
Keywords: git,log,stat,report,commit,github,audit,statistics,data-visualization
Classifier: Development Status :: 5 - Production/Stable
Classifier: Topic :: Office/Business :: Financial :: Investment
Classifier: Topic :: Software Development :: Version Control :: Git
Classifier: Intended Audience :: Developers
Classifier: Intended Audience :: Information Technology
Classifier: Intended Audience :: System Administrators
Classifier: Natural Language :: Chinese (Simplified)
Classifier: Natural Language :: English
Classifier: Natural Language :: German
Classifier: Natural Language :: Japanese
Classifier: Natural Language :: Korean
Classifier: Natural Language :: Portuguese
Classifier: Natural Language :: Russian
Classifier: Natural Language :: Spanish
Classifier: Operating System :: OS Independent
Classifier: Environment :: Web Environment
Classifier: Programming Language :: JavaScript
Classifier: Programming Language :: Python
Requires-Python: >=3.6
Dynamic: author
Dynamic: home-page
Dynamic: requires-python
